LICENSE.txt
MANIFEST.in
README.rst
setup.py
twiceredis/__init__.py
twiceredis/client.py
twiceredis.egg-info/PKG-INFO
twiceredis.egg-info/SOURCES.txt
twiceredis.egg-info/dependency_links.txt
twiceredis.egg-info/requires.txt
twiceredis.egg-info/top_level.txt