Metadata-Version: 1.1
Name: twiceredis
Version: 1.0.7
Summary: sentinel pool backed read and write redis client
Home-page: https://github.com/tr3buchet/twiceredis
Author: Trey Morris
Author-email: trey@treymorris.com
License: Apache Software License
Keywords: redis
Platform: UNKNOWN
Classifier: Development Status :: 5 - Production/Stable
Classifier: License :: OSI Approved :: Apache Software License
